{"data": {"uuid": "8dd43240-edf2-6739-e809-557609e755d9", "name": "HA EUN HO", "mmsi": "440012050", "imo": null, "eni": null, "country_iso": "KR", "type": "Fishing", "type_specific": "Fishing", "positions": [{"lat": 37.451953333333336, "lon": 126.325865, "speed": 0.2, "course": 228.8, "heading": 511, "destination": "", "last_position_epoch": 1716508288, "last_position_UTC": "2024-05-23T23:51:28Z"}, {"lat": 37.451953333333336, "lon": 126.32586833333333, "speed": 0.1, "course": 208, "heading": 511, "destination": "", "last_position_epoch": 1716507568, "last_position_UTC": "2024-05-23T23:39:28Z"}, {"lat": 37.45195833333333, "lon": 126.32588, "speed": 0.1, "course": 224.2, "heading": 511, "destination": "", "last_position_epoch": 1716505047, "last_position_UTC": "2024-05-23T22:57:27Z"}, {"lat": 37.451973333333335, "lon": 126.32588333333334, "speed": 0.1, "course": 213, "heading": 511, "destination": "", "last_position_epoch": 1716503968, "last_position_UTC": "2024-05-23T22:39:28Z"}, {"lat": 37.44866666666667, "lon": 126.34114833333334, "speed": 10.9, "course": 286.8, "heading": 511, "destination": "", "last_position_epoch": 1716502018, "last_position_UTC": "2024-05-23T22:06:58Z"}, {"lat": 37.45481, "lon": 126.320705, "speed": 2.4, "course": 330.8, "heading": 511, "destination": "", "last_position_epoch": 1716496333, "last_position_UTC": "2024-05-23T20:32:13Z"}, {"lat": 37.452985, "lon": 126.32320333333334, "speed": 0.3, "course": 323.6, "heading": 511, "destination": "", "last_position_epoch": 1716494536, "last_position_UTC": "2024-05-23T20:02:16Z"}, {"lat": 37.44805, "lon": 126.33382333333333, "speed": 7.5, "course": 262.1, "heading": 511, "destination": "", "last_position_epoch": 1716488845, "last_position_UTC": "2024-05-23T18:27:25Z"}, {"lat": 37.445211666666665, "lon": 126.34108, "speed": 0.2, "course": 326.2, "heading": 511, "destination": "", "last_position_epoch": 1716487169, "last_position_UTC": "2024-05-23T17:59:29Z"}, {"lat": 37.44524, "lon": 126.3445, "speed": 0.1, "course": 351, "heading": null, "destination": "CLASS B", "last_position_epoch": 1716477600, "last_position_UTC": "2024-05-23T15:20:00Z"}, {"lat": 37.44481, "lon": 126.34436166666667, "speed": 0.2, "course": 16, "heading": 511, "destination": "", "last_position_epoch": 1716475218, "last_position_UTC": "2024-05-23T14:40:18Z"}, {"lat": 37.44431, "lon": 126.34401833333334, "speed": 0.2, "course": 124.8, "heading": 511, "destination": "", "last_position_epoch": 1716472338, "last_position_UTC": "2024-05-23T13:52:18Z"}, {"lat": 37.44428666666666, "lon": 126.34391833333333, "speed": 0.1, "course": 147.5, "heading": 511, "destination": "", "last_position_epoch": 1716471257, "last_position_UTC": "2024-05-23T13:34:17Z"}, {"lat": 37.44426833333333, "lon": 126.34390333333333, "speed": 0.2, "course": 200, "heading": 511, "destination": "", "last_position_epoch": 1716469938, "last_position_UTC": "2024-05-23T13:12:18Z"}, {"lat": 37.444815, "lon": 126.328385, "speed": 8.8, "course": 308.4, "heading": 511, "destination": "", "last_position_epoch": 1716465384, "last_position_UTC": "2024-05-23T11:56:24Z"}, {"lat": 37.44268, "lon": 126.3309, "speed": 0.1, "course": 289, "heading": null, "destination": "CLASS B", "last_position_epoch": 1716457620, "last_position_UTC": "2024-05-23T09:47:00Z"}, {"lat": 37.44974, "lon": 126.3313, "speed": 0, "course": 129, "heading": null, "destination": "CLASS B", "last_position_epoch": 1716452340, "last_position_UTC": "2024-05-23T08:19:00Z"}, {"lat": 37.444131666666664, "lon": 126.33192333333334, "speed": 0.1, "course": 5.8, "heading": 511, "destination": "", "last_position_epoch": 1716435621, "last_position_UTC": "2024-05-23T03:40:21Z"}, {"lat": 37.442948333333334, "lon": 126.33142333333333, "speed": 0.2, "course": 72.7, "heading": 511, "destination": "", "last_position_epoch": 1716432865, "last_position_UTC": "2024-05-23T02:54:25Z"}, {"lat": 37.443398333333334, "lon": 126.328345, "speed": 1, "course": 336.2, "heading": 511, "destination": "", "last_position_epoch": 1716431339, "last_position_UTC": "2024-05-23T02:28:59Z"}, {"lat": 37.44733333333333, "lon": 126.32476833333334, "speed": 0.3, "course": 51.8, "heading": 511, "destination": "", "last_position_epoch": 1716429000, "last_position_UTC": "2024-05-23T01:50:00Z"}, {"lat": 37.44298833333333, "lon": 126.339025, "speed": 0.5, "course": 100.6, "heading": 511, "destination": "", "last_position_epoch": 1716427353, "last_position_UTC": "2024-05-23T01:22:33Z"}, {"lat": 37.443171666666665, "lon": 126.33833333333334, "speed": 0.1, "course": 299.9, "heading": 511, "destination": "", "last_position_epoch": 1716422854, "last_position_UTC": "2024-05-23T00:07:34Z"}, {"lat": 37.44304, "lon": 126.33856333333334, "speed": 0.1, "course": 283.3, "heading": 511, "destination": "", "last_position_epoch": 1716421058, "last_position_UTC": "2024-05-22T23:37:38Z"}, {"lat": 37.44297666666667, "lon": 126.33891333333334, "speed": 0.2, "course": 275.8, "heading": 511, "destination": "", "last_position_epoch": 1716419434, "last_position_UTC": "2024-05-22T23:10:34Z"}, {"lat": 37.44296, "lon": 126.33918, "speed": 0, "course": 277.9, "heading": 511, "destination": "", "last_position_epoch": 1716416912, "last_position_UTC": "2024-05-22T22:28:32Z"}, {"lat": 37.44296333333333, "lon": 126.33918833333334, "speed": 0, "course": 273.8, "heading": 511, "destination": "", "last_position_epoch": 1716415654, "last_position_UTC": "2024-05-22T22:07:34Z"}, {"lat": 37.44296666666666, "lon": 126.33944666666666, "speed": 0.1, "course": 231.8, "heading": 511, "destination": "", "last_position_epoch": 1716413853, "last_position_UTC": "2024-05-22T21:37:33Z"}, {"lat": 37.44350333333333, "lon": 126.33983, "speed": 0.1, "course": 241, "heading": 511, "destination": "", "last_position_epoch": 1716411872, "last_position_UTC": "2024-05-22T21:04:32Z"}, {"lat": 37.44556, "lon": 126.3444, "speed": 0.1, "course": 357, "heading": null, "destination": "CLASS B", "last_position_epoch": 1716401820, "last_position_UTC": "2024-05-22T18:17:00Z"}, {"lat": 37.44502333333333, "lon": 126.34425166666666, "speed": 0.1, "course": 359.1, "heading": 511, "destination": "", "last_position_epoch": 1716387698, "last_position_UTC": "2024-05-22T14:21:38Z"}, {"lat": 37.444426666666665, "lon": 126.34419166666666, "speed": 0.1, "course": 289.2, "heading": 511, "destination": "", "last_position_epoch": 1716386437, "last_position_UTC": "2024-05-22T14:00:37Z"}, {"lat": 37.444335, "lon": 126.34394666666667, "speed": 0, "course": 261.2, "heading": 511, "destination": "", "last_position_epoch": 1716384997, "last_position_UTC": "2024-05-22T13:36:37Z"}, {"lat": 37.44433, "lon": 126.34386333333333, "speed": 0.1, "course": 261.2, "heading": 511, "destination": "", "last_position_epoch": 1716383558, "last_position_UTC": "2024-05-22T13:12:38Z"}, {"lat": 37.44195833333333, "lon": 126.33418, "speed": 9.2, "course": 88.7, "heading": 511, "destination": "", "last_position_epoch": 1716382060, "last_position_UTC": "2024-05-22T12:47:40Z"}, {"lat": 37.44747666666667, "lon": 126.324695, "speed": 1, "course": 359.1, "heading": 511, "destination": "", "last_position_epoch": 1716378799, "last_position_UTC": "2024-05-22T11:53:19Z"}, {"lat": 37.45196166666667, "lon": 126.32584166666666, "speed": 0, "course": 198.5, "heading": 511, "destination": "", "last_position_epoch": 1716378083, "last_position_UTC": "2024-05-22T11:41:23Z"}, {"lat": 37.45196166666667, "lon": 126.32583833333334, "speed": 0, "course": 170.5, "heading": 511, "destination": "", "last_position_epoch": 1716376101, "last_position_UTC": "2024-05-22T11:08:21Z"}, {"lat": 37.451903333333334, "lon": 126.32584166666666, "speed": 3.1, "course": 31.1, "heading": 511, "destination": "", "last_position_epoch": 1716374452, "last_position_UTC": "2024-05-22T10:40:52Z"}, {"lat": 37.446373333333334, "lon": 126.32667166666667, "speed": 0.1, "course": 110.2, "heading": 511, "destination": "", "last_position_epoch": 1716372956, "last_position_UTC": "2024-05-22T10:15:56Z"}, {"lat": 37.446731666666665, "lon": 126.32574666666666, "speed": 0, "course": 132.6, "heading": 511, "destination": "", "last_position_epoch": 1716370796, "last_position_UTC": "2024-05-22T09:39:56Z"}, {"lat": 37.44712333333333, "lon": 126.32535166666666, "speed": 0, "course": 135, "heading": 511, "destination": "", "last_position_epoch": 1716368816, "last_position_UTC": "2024-05-22T09:06:56Z"}, {"lat": 37.44752, "lon": 126.32471333333334, "speed": 0.2, "course": 79.1, "heading": 511, "destination": "", "last_position_epoch": 1716367557, "last_position_UTC": "2024-05-22T08:45:57Z"}, {"lat": 37.41594666666667, "lon": 126.40654333333333, "speed": 10, "course": 286.7, "heading": 511, "destination": "", "last_position_epoch": 1716365457, "last_position_UTC": "2024-05-22T08:10:57Z"}, {"lat": 37.411395, "lon": 126.48862833333334, "speed": 8.2, "course": 280.9, "heading": 511, "destination": "", "last_position_epoch": 1716363776, "last_position_UTC": "2024-05-22T07:42:56Z"}, {"lat": 37.45707, "lon": 126.597, "speed": 0.4, "course": 26, "heading": null, "destination": "CLASS B", "last_position_epoch": 1716324600, "last_position_UTC": "2024-05-21T20:50:00Z"}, {"lat": 37.44903, "lon": 126.58375833333334, "speed": 7.4, "course": 37.5, "heading": 511, "destination": "", "last_position_epoch": 1716323972, "last_position_UTC": "2024-05-21T20:39:32Z"}, {"lat": 37.412863333333334, "lon": 126.52785333333334, "speed": 8.4, "course": 75, "heading": 511, "destination": "", "last_position_epoch": 1716322351, "last_position_UTC": "2024-05-21T20:12:31Z"}, {"lat": 37.41950666666666, "lon": 126.44784833333334, "speed": 7.2, "course": 87, "heading": 511, "destination": "", "last_position_epoch": 1716320521, "last_position_UTC": "2024-05-21T19:42:01Z"}, {"lat": 37.42682166666667, "lon": 126.37083166666666, "speed": 7.6, "course": 136.3, "heading": 511, "destination": "", "last_position_epoch": 1716318512, "last_position_UTC": "2024-05-21T19:08:32Z"}, {"lat": 37.445115, "lon": 126.34117333333333, "speed": 0.2, "course": 161.6, "heading": 511, "destination": "", "last_position_epoch": 1716316508, "last_position_UTC": "2024-05-21T18:35:08Z"}, {"lat": 37.43882166666667, "lon": 126.31310833333333, "speed": 10.9, "course": 44.7, "heading": 511, "destination": "", "last_position_epoch": 1716312620, "last_position_UTC": "2024-05-21T17:30:20Z"}, {"lat": 37.27753666666667, "lon": 126.037005, "speed": 9.8, "course": 288.4, "heading": 511, "destination": "", "last_position_epoch": 1716151046, "last_position_UTC": "2024-05-19T20:37:26Z"}, {"lat": 37.256825, "lon": 126.12523333333333, "speed": 0.1, "course": 3.1, "heading": 511, "destination": "", "last_position_epoch": 1716146280, "last_position_UTC": "2024-05-19T19:18:00Z"}, {"lat": 37.25684, "lon": 126.12524666666667, "speed": 0.1, "course": 327.8, "heading": 511, "destination": "", "last_position_epoch": 1716145560, "last_position_UTC": "2024-05-19T19:06:00Z"}, {"lat": 37.25683, "lon": 126.12520333333333, "speed": 0.1, "course": 298.5, "heading": 511, "destination": "", "last_position_epoch": 1716141780, "last_position_UTC": "2024-05-19T18:03:00Z"}, {"lat": 37.25680333333333, "lon": 126.12517166666667, "speed": 0, "course": 331.7, "heading": 511, "destination": "", "last_position_epoch": 1716140160, "last_position_UTC": "2024-05-19T17:36:00Z"}, {"lat": 37.25223166666667, "lon": 126.11949666666666, "speed": 0.6, "course": 264.8, "heading": 511, "destination": "", "last_position_epoch": 1716132217, "last_position_UTC": "2024-05-19T15:23:37Z"}, {"lat": 37.255365, "lon": 126.12136166666667, "speed": 0.1, "course": 127.9, "heading": 511, "destination": "", "last_position_epoch": 1716125230, "last_position_UTC": "2024-05-19T13:27:10Z"}, {"lat": 37.25580333333333, "lon": 126.121465, "speed": 1, "course": 243.6, "heading": 511, "destination": "", "last_position_epoch": 1716122503, "last_position_UTC": "2024-05-19T12:41:43Z"}, {"lat": 37.37991, "lon": 126.0574, "speed": 0.9, "course": 119, "heading": null, "destination": "CLASS B", "last_position_epoch": 1716117480, "last_position_UTC": "2024-05-19T11:18:00Z"}, {"lat": 37.43311666666666, "lon": 126.26010666666667, "speed": 7.2, "course": 229.9, "heading": 511, "destination": "", "last_position_epoch": 1716093067, "last_position_UTC": "2024-05-19T04:31:07Z"}, {"lat": 37.44009333333333, "lon": 126.29534666666666, "speed": 7.5, "course": 247.5, "heading": 511, "destination": "", "last_position_epoch": 1716085554, "last_position_UTC": "2024-05-19T02:25:54Z"}, {"lat": 37.44329, "lon": 126.30779166666667, "speed": 0.2, "course": 4.4, "heading": 511, "destination": "", "last_position_epoch": 1716077343, "last_position_UTC": "2024-05-19T00:09:03Z"}, {"lat": 37.45867166666667, "lon": 126.31558666666666, "speed": 0.5, "course": 97.8, "heading": 511, "destination": "", "last_position_epoch": 1716073540, "last_position_UTC": "2024-05-18T23:05:40Z"}, {"lat": 37.45928333333333, "lon": 126.31368333333333, "speed": 0.1, "course": 357.3, "heading": 511, "destination": "", "last_position_epoch": 1716071020, "last_position_UTC": "2024-05-18T22:23:40Z"}, {"lat": 37.46188166666666, "lon": 126.31237666666667, "speed": 1, "course": 331.9, "heading": 511, "destination": "", "last_position_epoch": 1716068020, "last_position_UTC": "2024-05-18T21:33:40Z"}, {"lat": 37.451638333333335, "lon": 126.32155333333333, "speed": 0, "course": 107.7, "heading": 511, "destination": "", "last_position_epoch": 1716066674, "last_position_UTC": "2024-05-18T21:11:14Z"}, {"lat": 37.45227166666667, "lon": 126.32009666666667, "speed": 0.1, "course": 224.6, "heading": 511, "destination": "", "last_position_epoch": 1716063074, "last_position_UTC": "2024-05-18T20:11:14Z"}, {"lat": 37.45222666666667, "lon": 126.32019, "speed": 0.1, "course": 215.4, "heading": 511, "destination": "", "last_position_epoch": 1716060194, "last_position_UTC": "2024-05-18T19:23:14Z"}, {"lat": 37.452423333333336, "lon": 126.32033166666666, "speed": 0.2, "course": 205.7, "heading": 511, "destination": "", "last_position_epoch": 1716058035, "last_position_UTC": "2024-05-18T18:47:15Z"}, {"lat": 37.452731666666665, "lon": 126.32054333333333, "speed": 0.3, "course": 199.7, "heading": 511, "destination": "", "last_position_epoch": 1716057314, "last_position_UTC": "2024-05-18T18:35:14Z"}, {"lat": 37.4536, "lon": 126.32075166666667, "speed": 0, "course": 330.3, "heading": 511, "destination": "", "last_position_epoch": 1716054674, "last_position_UTC": "2024-05-18T17:51:14Z"}, {"lat": 37.447631666666666, "lon": 126.32825833333334, "speed": 0.4, "course": 258.4, "heading": 511, "destination": "", "last_position_epoch": 1716053599, "last_position_UTC": "2024-05-18T17:33:19Z"}, {"lat": 37.447556666666664, "lon": 126.33582333333334, "speed": 9, "course": 240.3, "heading": 511, "destination": "", "last_position_epoch": 1716052043, "last_position_UTC": "2024-05-18T17:07:23Z"}, {"lat": 37.43638, "lon": 126.35521333333334, "speed": 9.4, "course": 311, "heading": 511, "destination": "", "last_position_epoch": 1716050273, "last_position_UTC": "2024-05-18T16:37:53Z"}, {"lat": 37.41240166666667, "lon": 126.42948166666666, "speed": 9.4, "course": 264.8, "heading": 511, "destination": "", "last_position_epoch": 1716048773, "last_position_UTC": "2024-05-18T16:12:53Z"}, {"lat": 37.41316166666667, "lon": 126.53037166666667, "speed": 8.3, "course": 256.1, "heading": 511, "destination": "", "last_position_epoch": 1716046672, "last_position_UTC": "2024-05-18T15:37:52Z"}]}, "meta": {"duration": 0.008524762, "endpoint": "/api/v0/vessel_history", "success": true}}