{"data": {"uuid": "1b094eb4-01a9-1c95-5477-92d81c97affb", "name": "MO BI DIC", "mmsi": "440714700", "imo": null, "eni": null, "country_iso": "KR", "type": "Fishing", "type_specific": "Fishing", "positions": [{"lat": 37.38146, "lon": 126.4775, "speed": 11.8, "course": 274, "heading": 274, "destination": "CLASS B", "last_position_epoch": 1716238020, "last_position_UTC": "2024-05-20T20:47:00Z"}, {"lat": 37.43497, "lon": 126.575, "speed": 11.4, "course": 218, "heading": 218, "destination": "CLASS B", "last_position_epoch": 1716236280, "last_position_UTC": "2024-05-20T20:18:00Z"}, {"lat": 37.44207, "lon": 126.5785, "speed": 11.1, "course": 40, "heading": 40, "destination": "CLASS B", "last_position_epoch": 1716193080, "last_position_UTC": "2024-05-20T08:18:00Z"}, {"lat": 37.36967, "lon": 126.4512, "speed": 1.4, "course": 198, "heading": 198, "destination": "CLASS B", "last_position_epoch": 1716153720, "last_position_UTC": "2024-05-19T21:22:00Z"}, {"lat": 37.37084, "lon": 126.4517, "speed": 1.1, "course": 232, "heading": 232, "destination": "CLASS B", "last_position_epoch": 1716151800, "last_position_UTC": "2024-05-19T20:50:00Z"}, {"lat": 37.39251, "lon": 126.5065, "speed": 11.3, "course": 241, "heading": 241, "destination": "CLASS B", "last_position_epoch": 1716150060, "last_position_UTC": "2024-05-19T20:21:00Z"}, {"lat": 37.41225, "lon": 126.5455, "speed": 11.3, "course": 59, "heading": 59, "destination": "CLASS B", "last_position_epoch": 1716108600, "last_position_UTC": "2024-05-19T08:50:00Z"}]}, "meta": {"duration": 0.002881694, "endpoint": "/api/v0/vessel_history", "success": true}}